zipminator/.DS_Store
zipminator/Untitled.ipynb
zipminator/Untitled1.ipynb
zipminator/Untitled2.ipynb
zipminator/Untitled3.ipynb
zipminator/Untitled4.ipynb
zipminator/__init__.py
zipminator/__version__.py
zipminator/anonymise.py
zipminator/audit_trail.py
zipminator/compliance_check.py
zipminator/mask.py
zipminator/regex_patterns.py
zipminator/self_destruct.py
zipminator/unzipit.py
zipminator/zipit.py
zipminator-0.3.0.dist-info/LICENSE
zipminator-0.3.0.dist-info/WHEEL
zipminator-0.3.0.dist-info/METADATA
zipminator-0.3.0.dist-info/RECORD
