Metadata-Version: 2.1
Name: zipminator
Version: 0.3.0
Summary: Zipminator is a lightweight Python package for compressing, encrypting, and deleting password-protected Pandas DataFrames.
Home-page: https://qdaria.github.io/zipminator/
License: MIT
Keywords: pandas,compression,encryption,data-security
Author: Daniel Mo Houshmand
Author-email: mo@qdaria.com
Requires-Python: >=3.8,<4.0
Classifier: License :: OSI Approved :: MIT License
Classifier: Programming Language :: Python :: 3
Classifier: Programming Language :: Python :: 3.10
Classifier: Programming Language :: Python :: 3.8
Classifier: Programming Language :: Python :: 3.9
Requires-Dist: jupyter-sphinx (>=0.4.0,<0.5.0)
Requires-Dist: numpy (>=1.24.1,<2.0.0)
Requires-Dist: pandas (>=1.5.2,<2.0.0)
Requires-Dist: pyzipper (>=0.3.6,<0.4.0)
Project-URL: Documentation, https://qdaria.github.io/zipminator/
Project-URL: Repository, https://github.com/QDaria/zipminator
